foliant/preprocessors/apilinks/__init__.py
foliant/preprocessors/apilinks/apilinks.py
foliant/preprocessors/apilinks/classes.py
foliant/preprocessors/apilinks/constants.py
foliant/preprocessors/apilinks/tools.py
foliantcontrib.apilinks-1.2.6.dist-info/LICENSE
foliantcontrib.apilinks-1.2.6.dist-info/METADATA
foliantcontrib.apilinks-1.2.6.dist-info/WHEEL
foliantcontrib.apilinks-1.2.6.dist-info/top_level.txt
foliantcontrib.apilinks-1.2.6.dist-info/RECORD
